{
  "news": [
    {
      "id": "1",
      "title": "Cu Chi Tunnels Luxury Tour - Morning or Afternoon",
      "content": "Hear stories of the American-Vietnam war as you discover the maze-like Cu Chi Tunnels, a 136-mile (220 kilometers) network of underground tunnels used by the Viet Cong soldiers. Step back in time as you peek into the old storage areas, poke your head through camouflaged trapdoors, and crawl through military supply tunnels.Read more about Cu Chi Tunnels Luxury Tour - Morning or Afternoon - https://www.viator.com/tours/Ho-Chi-Minh-City/Cu-Chi-Tunnels-halfday-small-group/d352-20086P1?mcid=56757",
      "image": "cuchi.jpg",
      "author": "Tan Phuoc",
      "date": "2004-08-07 16:32:01",
      "like": 39,
      "dislike": 19,
      "haha": 38,
      "star": 0,
      "views": 3591,
      "undefined": 5
    },
    {
      "id": "2",
      "title": "Ha Long Bay Cruise Day Tour - Cave, Kayaking, Swimming & Lunch",
      "content": "Escape Hanoi and discover Ha Long Bay, the Ha Long Warf, Sung Sot Cave, and the tranquil Ti Top Island. Kayak at Luon Cave, and swim in the blue waters of the crescent-shaped Titov beach. Feel the warm sunshine and the cool breeze while cruising along Ha Long Bay Explore the shimmering stalactites embodying unique shapes of the Sung Sot cave Uncover the stunning beauty of the Luon Cave while kayaking on the blue water Enjoy a sunset party on the boat with red wine, cake, fruits, and more Spend some time in the water or trek to the Titop peak for panoramic views Read more about Ha Long Bay Cruise Day Tour - Cave, Kayaking, Swimming & Lunch - https://www.viator.com/tours/Hanoi/Ha-Long-Bay-Bai-Tu-Long-2-days-cruise/d351-102255P1?mcid=56757",
      "image": "halong.jpg",
      "author": "Tan Phuong",
      "date": "2008-12-05 17:38:45",
      "like": 3,
      "dislike": 7,
      "haha": 3,
      "star": 0,
      "views": 163
    },
    {
      "id": "3",
      "title": "Morning Small group to Marble Mountains - Am Phu Cave - Monkey Mountain",
      "content": "Explore the Marble Mountains from Hoi An on this small-group guided morning tour that includes transport. Visit Am Phu Cave, Monkey Mountain, and the largest Lady Buddha statue in Vietnam, with an English speaking guide to provide insightful commentary. Includes round-trip transfers, lunch, and entrance fees to Marble Mountains.Read more about Morning Small group to Marble Mountains - Am Phu Cave - Monkey Mountain - https://www.viator.com/tours/Da-Nang/Morning-Small-group-to-Marble-Mountains-Am-Phu-Cave-Monkey-Mountain/d4680-104142P3?mcid=56757",
      "image": "amphu.jpg",
      "author": "Tan phu",
      "date": "2015-12-07 18:00:00",
      "like": 0,
      "dislike": 0,
      "haha": 0,
      "star": 0,
      "views": 27
    }
  ],
  "productss": [
    {
      "id": "1",
      "name": "Giày thể thao nam Nike1",
      "price": 150,
      "image": "giay1.png",
      "views": 0
    },
    {
      "id": "2",
      "name": "Giày thể thao nam Nike2",
      "price": 170,
      "image": "giay2.png",
      "views": 0
    },
    {
      "id": "3",
      "name": "Giày thể thao nam Nike3",
      "price": 160,
      "image": "giay3.png",
      "views": 0
    },
    {
      "id": "4",
      "name": "Giày thể thao nam Nike4",
      "price": 160,
      "image": "giay4.png",
      "views": 0
    },
    {
      "id": "5",
      "name": "Giày thể thao nam Nike5",
      "price": 150,
      "image": "giay5.png",
      "views": 0
    },
    {
      "id": "6",
      "name": "Giày thể thao nam Nike6",
      "price": 170,
      "image": "giay6.png",
      "views": 0
    },
    {
      "id": "7",
      "name": "Giày thể thao nam Nike7",
      "price": 160,
      "image": "giay7.png",
      "views": 0
    },
    {
      "id": "8",
      "name": "Giày thể thao nam Nike8",
      "price": 160,
      "image": "giay8.png",
      "views": 0
    },
    {
      "id": "9",
      "name": "Giày thể thao nam Nike8",
      "price": 160,
      "image": "giay9.png",
      "views": 0
    },
    {
      "id": "10",
      "name": "Giày thể thao nam Nike8",
      "price": 160,
      "image": "giay10.png",
      "views": 0
    },
    {
      "id": "11",
      "name": "Giày thể thao nam Nike8",
      "price": 160,
      "image": "giay11.png",
      "views": 0
    },
    {
      "id": "12",
      "name": "Giày thể thao nam Nike8",
      "price": 160,
      "image": "giayt1.png",
      "views": 0
    }
  ],
  "comments": [
    {
      "id": "4e1e",
      "idNews": "1",
      "idUser": "2",
      "name": "Văn Tấn Khair",
      "content": "ddddddddddddddddddddddddd",
      "date": "2024-04-03 19:47:35"
    },
    {
      "id": "15c3",
      "idNews": "1",
      "idUser": "1",
      "name": "Văn Tấn Phước",
      "content": "ss",
      "date": "2024-04-05 11:56:00"
    },
    {
      "id": "221a",
      "idNews": "1",
      "idUser": "1",
      "name": "Văn Tấn Phước",
      "content": "asd",
      "date": "2024-04-07 22:25:50"
    }
  ],
  "users": [
    {
      "id": "1",
      "name": "Văn Tấn Phước",
      "email": "phuoc@gmail.com",
      "password": "Phuoc@0708"
    }
  ],
  "orders": [
    {
      "id": "c8b8",
      "name": "323213",
      "idUser": "-1",
      "phone": 2343242,
      "address": "24234234",
      "products": [
        {
          "id": "1",
          "name": "Giày thể thao nam Nike1",
          "price": 150,
          "image": "giay1.png",
          "views": 0,
          "quantity": 5
        },
        {
          "id": "2",
          "name": "Giày thể thao nam Nike2",
          "price": 170,
          "image": "giay2.png",
          "views": 0,
          "quantity": 3
        },
        {
          "id": "3",
          "name": "Giày thể thao nam Nike3",
          "price": 160,
          "image": "giay3.png",
          "views": 0,
          "quantity": 2
        },
        {
          "id": "4",
          "name": "Giày thể thao nam Nike4",
          "price": 160,
          "image": "giay4.png",
          "views": 0,
          "quantity": 1
        },
        {
          "id": "5",
          "name": "Giày thể thao nam Nike5",
          "price": 150,
          "image": "giay5.png",
          "views": 0,
          "quantity": 2
        },
        {
          "id": "6",
          "name": "Giày thể thao nam Nike6",
          "price": 170,
          "image": "giay6.png",
          "views": 0,
          "quantity": 2
        }
      ],
      "total": 2380,
      "date": "2024-04-05 13:45:43",
      "status": "order"
    },
    {
      "id": "37ed",
      "name": "323213",
      "idUser": "-1",
      "phone": 2343242,
      "address": "24234234",
      "products": [
        {
          "id": "1",
          "name": "Giày thể thao nam Nike1",
          "price": 150,
          "image": "giay1.png",
          "views": 0,
          "quantity": 5
        },
        {
          "id": "2",
          "name": "Giày thể thao nam Nike2",
          "price": 170,
          "image": "giay2.png",
          "views": 0,
          "quantity": 3
        },
        {
          "id": "3",
          "name": "Giày thể thao nam Nike3",
          "price": 160,
          "image": "giay3.png",
          "views": 0,
          "quantity": 2
        },
        {
          "id": "4",
          "name": "Giày thể thao nam Nike4",
          "price": 160,
          "image": "giay4.png",
          "views": 0,
          "quantity": 1
        },
        {
          "id": "5",
          "name": "Giày thể thao nam Nike5",
          "price": 150,
          "image": "giay5.png",
          "views": 0,
          "quantity": 2
        },
        {
          "id": "6",
          "name": "Giày thể thao nam Nike6",
          "price": 170,
          "image": "giay6.png",
          "views": 0,
          "quantity": 2
        }
      ],
      "total": 2380,
      "date": "2024-04-05 13:45:44",
      "status": "order"
    },
    {
      "id": "f640",
      "name": "323213",
      "idUser": "-1",
      "phone": 2343242,
      "address": "24234234",
      "products": [
        {
          "id": "1",
          "name": "Giày thể thao nam Nike1",
          "price": 150,
          "image": "giay1.png",
          "views": 0,
          "quantity": 5
        },
        {
          "id": "2",
          "name": "Giày thể thao nam Nike2",
          "price": 170,
          "image": "giay2.png",
          "views": 0,
          "quantity": 3
        },
        {
          "id": "3",
          "name": "Giày thể thao nam Nike3",
          "price": 160,
          "image": "giay3.png",
          "views": 0,
          "quantity": 2
        },
        {
          "id": "4",
          "name": "Giày thể thao nam Nike4",
          "price": 160,
          "image": "giay4.png",
          "views": 0,
          "quantity": 1
        },
        {
          "id": "5",
          "name": "Giày thể thao nam Nike5",
          "price": 150,
          "image": "giay5.png",
          "views": 0,
          "quantity": 2
        },
        {
          "id": "6",
          "name": "Giày thể thao nam Nike6",
          "price": 170,
          "image": "giay6.png",
          "views": 0,
          "quantity": 2
        }
      ],
      "total": 2380,
      "date": "2024-04-05 13:45:44",
      "status": "order"
    },
    {
      "id": "4e92",
      "name": "323213",
      "idUser": "-1",
      "phone": 2343242,
      "address": "24234234",
      "products": [
        {
          "id": "1",
          "name": "Giày thể thao nam Nike1",
          "price": 150,
          "image": "giay1.png",
          "views": 0,
          "quantity": 5
        },
        {
          "id": "2",
          "name": "Giày thể thao nam Nike2",
          "price": 170,
          "image": "giay2.png",
          "views": 0,
          "quantity": 3
        },
        {
          "id": "3",
          "name": "Giày thể thao nam Nike3",
          "price": 160,
          "image": "giay3.png",
          "views": 0,
          "quantity": 2
        },
        {
          "id": "4",
          "name": "Giày thể thao nam Nike4",
          "price": 160,
          "image": "giay4.png",
          "views": 0,
          "quantity": 1
        },
        {
          "id": "5",
          "name": "Giày thể thao nam Nike5",
          "price": 150,
          "image": "giay5.png",
          "views": 0,
          "quantity": 2
        },
        {
          "id": "6",
          "name": "Giày thể thao nam Nike6",
          "price": 170,
          "image": "giay6.png",
          "views": 0,
          "quantity": 2
        }
      ],
      "total": 2380,
      "date": "2024-04-05 13:45:44",
      "status": "order"
    },
    {
      "id": "ba66",
      "name": "323213",
      "idUser": "-1",
      "phone": 2343242,
      "address": "24234234",
      "products": [
        {
          "id": "1",
          "name": "Giày thể thao nam Nike1",
          "price": 150,
          "image": "giay1.png",
          "views": 0,
          "quantity": 5
        },
        {
          "id": "2",
          "name": "Giày thể thao nam Nike2",
          "price": 170,
          "image": "giay2.png",
          "views": 0,
          "quantity": 3
        },
        {
          "id": "3",
          "name": "Giày thể thao nam Nike3",
          "price": 160,
          "image": "giay3.png",
          "views": 0,
          "quantity": 2
        },
        {
          "id": "4",
          "name": "Giày thể thao nam Nike4",
          "price": 160,
          "image": "giay4.png",
          "views": 0,
          "quantity": 1
        },
        {
          "id": "5",
          "name": "Giày thể thao nam Nike5",
          "price": 150,
          "image": "giay5.png",
          "views": 0,
          "quantity": 2
        },
        {
          "id": "6",
          "name": "Giày thể thao nam Nike6",
          "price": 170,
          "image": "giay6.png",
          "views": 0,
          "quantity": 2
        }
      ],
      "total": 2380,
      "date": "2024-04-05 13:45:44",
      "status": "order"
    },
    {
      "id": "8a3d",
      "name": "323213",
      "idUser": "-1",
      "phone": 2343242,
      "address": "24234234",
      "products": [
        {
          "id": "1",
          "name": "Giày thể thao nam Nike1",
          "price": 150,
          "image": "giay1.png",
          "views": 0,
          "quantity": 5
        },
        {
          "id": "2",
          "name": "Giày thể thao nam Nike2",
          "price": 170,
          "image": "giay2.png",
          "views": 0,
          "quantity": 3
        },
        {
          "id": "3",
          "name": "Giày thể thao nam Nike3",
          "price": 160,
          "image": "giay3.png",
          "views": 0,
          "quantity": 2
        },
        {
          "id": "4",
          "name": "Giày thể thao nam Nike4",
          "price": 160,
          "image": "giay4.png",
          "views": 0,
          "quantity": 1
        },
        {
          "id": "5",
          "name": "Giày thể thao nam Nike5",
          "price": 150,
          "image": "giay5.png",
          "views": 0,
          "quantity": 2
        },
        {
          "id": "6",
          "name": "Giày thể thao nam Nike6",
          "price": 170,
          "image": "giay6.png",
          "views": 0,
          "quantity": 2
        }
      ],
      "total": 2380,
      "date": "2024-04-05 13:45:44",
      "status": "order"
    },
    {
      "id": "149b",
      "name": "23131",
      "idUser": "-1",
      "phone": 4143242,
      "address": "ưrưẻwrư",
      "products": [
        {
          "id": "1",
          "name": "Giày thể thao nam Nike1",
          "price": 150,
          "image": "giay1.png",
          "views": 0,
          "quantity": 5
        },
        {
          "id": "2",
          "name": "Giày thể thao nam Nike2",
          "price": 170,
          "image": "giay2.png",
          "views": 0,
          "quantity": 3
        },
        {
          "id": "3",
          "name": "Giày thể thao nam Nike3",
          "price": 160,
          "image": "giay3.png",
          "views": 0,
          "quantity": 2
        },
        {
          "id": "4",
          "name": "Giày thể thao nam Nike4",
          "price": 160,
          "image": "giay4.png",
          "views": 0,
          "quantity": 1
        },
        {
          "id": "5",
          "name": "Giày thể thao nam Nike5",
          "price": 150,
          "image": "giay5.png",
          "views": 0,
          "quantity": 2
        },
        {
          "id": "6",
          "name": "Giày thể thao nam Nike6",
          "price": 170,
          "image": "giay6.png",
          "views": 0,
          "quantity": 2
        }
      ],
      "total": 2380,
      "date": "2024-04-05 13:49:10",
      "status": "order"
    },
    {
      "id": "daad",
      "name": "23131",
      "idUser": "-1",
      "phone": 4143242,
      "address": "ưrưẻwrư",
      "products": [
        {
          "id": "1",
          "name": "Giày thể thao nam Nike1",
          "price": 150,
          "image": "giay1.png",
          "views": 0,
          "quantity": 5
        },
        {
          "id": "2",
          "name": "Giày thể thao nam Nike2",
          "price": 170,
          "image": "giay2.png",
          "views": 0,
          "quantity": 3
        },
        {
          "id": "3",
          "name": "Giày thể thao nam Nike3",
          "price": 160,
          "image": "giay3.png",
          "views": 0,
          "quantity": 2
        },
        {
          "id": "4",
          "name": "Giày thể thao nam Nike4",
          "price": 160,
          "image": "giay4.png",
          "views": 0,
          "quantity": 1
        },
        {
          "id": "5",
          "name": "Giày thể thao nam Nike5",
          "price": 150,
          "image": "giay5.png",
          "views": 0,
          "quantity": 2
        },
        {
          "id": "6",
          "name": "Giày thể thao nam Nike6",
          "price": 170,
          "image": "giay6.png",
          "views": 0,
          "quantity": 2
        }
      ],
      "total": 2380,
      "date": "2024-04-05 13:49:11",
      "status": "order"
    },
    {
      "id": "6678",
      "name": "23131",
      "idUser": "-1",
      "phone": 4143242,
      "address": "ưrưẻwrư",
      "products": [
        {
          "id": "1",
          "name": "Giày thể thao nam Nike1",
          "price": 150,
          "image": "giay1.png",
          "views": 0,
          "quantity": 5
        },
        {
          "id": "2",
          "name": "Giày thể thao nam Nike2",
          "price": 170,
          "image": "giay2.png",
          "views": 0,
          "quantity": 3
        },
        {
          "id": "3",
          "name": "Giày thể thao nam Nike3",
          "price": 160,
          "image": "giay3.png",
          "views": 0,
          "quantity": 2
        },
        {
          "id": "4",
          "name": "Giày thể thao nam Nike4",
          "price": 160,
          "image": "giay4.png",
          "views": 0,
          "quantity": 1
        },
        {
          "id": "5",
          "name": "Giày thể thao nam Nike5",
          "price": 150,
          "image": "giay5.png",
          "views": 0,
          "quantity": 2
        },
        {
          "id": "6",
          "name": "Giày thể thao nam Nike6",
          "price": 170,
          "image": "giay6.png",
          "views": 0,
          "quantity": 2
        }
      ],
      "total": 2380,
      "date": "2024-04-05 13:49:11",
      "status": "order"
    },
    {
      "id": "9b50",
      "name": "23131",
      "idUser": "-1",
      "phone": 4143242,
      "address": "ưrưẻwrư",
      "products": [
        {
          "id": "1",
          "name": "Giày thể thao nam Nike1",
          "price": 150,
          "image": "giay1.png",
          "views": 0,
          "quantity": 5
        },
        {
          "id": "2",
          "name": "Giày thể thao nam Nike2",
          "price": 170,
          "image": "giay2.png",
          "views": 0,
          "quantity": 3
        },
        {
          "id": "3",
          "name": "Giày thể thao nam Nike3",
          "price": 160,
          "image": "giay3.png",
          "views": 0,
          "quantity": 2
        },
        {
          "id": "4",
          "name": "Giày thể thao nam Nike4",
          "price": 160,
          "image": "giay4.png",
          "views": 0,
          "quantity": 1
        },
        {
          "id": "5",
          "name": "Giày thể thao nam Nike5",
          "price": 150,
          "image": "giay5.png",
          "views": 0,
          "quantity": 2
        },
        {
          "id": "6",
          "name": "Giày thể thao nam Nike6",
          "price": 170,
          "image": "giay6.png",
          "views": 0,
          "quantity": 2
        }
      ],
      "total": 2380,
      "date": "2024-04-05 13:49:11",
      "status": "order"
    },
    {
      "id": "5e87",
      "name": "23131",
      "idUser": "-1",
      "phone": 4143242,
      "address": "ưrưẻwrư",
      "products": [
        {
          "id": "1",
          "name": "Giày thể thao nam Nike1",
          "price": 150,
          "image": "giay1.png",
          "views": 0,
          "quantity": 5
        },
        {
          "id": "2",
          "name": "Giày thể thao nam Nike2",
          "price": 170,
          "image": "giay2.png",
          "views": 0,
          "quantity": 3
        },
        {
          "id": "3",
          "name": "Giày thể thao nam Nike3",
          "price": 160,
          "image": "giay3.png",
          "views": 0,
          "quantity": 2
        },
        {
          "id": "4",
          "name": "Giày thể thao nam Nike4",
          "price": 160,
          "image": "giay4.png",
          "views": 0,
          "quantity": 1
        },
        {
          "id": "5",
          "name": "Giày thể thao nam Nike5",
          "price": 150,
          "image": "giay5.png",
          "views": 0,
          "quantity": 2
        },
        {
          "id": "6",
          "name": "Giày thể thao nam Nike6",
          "price": 170,
          "image": "giay6.png",
          "views": 0,
          "quantity": 2
        }
      ],
      "total": 2380,
      "date": "2024-04-05 13:49:11",
      "status": "order"
    },
    {
      "id": "e1fe",
      "name": "23131",
      "idUser": "-1",
      "phone": 4143242,
      "address": "ưrưẻwrư",
      "products": [
        {
          "id": "1",
          "name": "Giày thể thao nam Nike1",
          "price": 150,
          "image": "giay1.png",
          "views": 0,
          "quantity": 5
        },
        {
          "id": "2",
          "name": "Giày thể thao nam Nike2",
          "price": 170,
          "image": "giay2.png",
          "views": 0,
          "quantity": 3
        },
        {
          "id": "3",
          "name": "Giày thể thao nam Nike3",
          "price": 160,
          "image": "giay3.png",
          "views": 0,
          "quantity": 2
        },
        {
          "id": "4",
          "name": "Giày thể thao nam Nike4",
          "price": 160,
          "image": "giay4.png",
          "views": 0,
          "quantity": 1
        },
        {
          "id": "5",
          "name": "Giày thể thao nam Nike5",
          "price": 150,
          "image": "giay5.png",
          "views": 0,
          "quantity": 2
        },
        {
          "id": "6",
          "name": "Giày thể thao nam Nike6",
          "price": 170,
          "image": "giay6.png",
          "views": 0,
          "quantity": 2
        }
      ],
      "total": 2380,
      "date": "2024-04-05 13:49:12",
      "status": "order"
    },
    {
      "id": "0751",
      "name": "23131",
      "idUser": "-1",
      "phone": 4143242,
      "address": "ưrưẻwrư",
      "products": [
        {
          "id": "1",
          "name": "Giày thể thao nam Nike1",
          "price": 150,
          "image": "giay1.png",
          "views": 0,
          "quantity": 5
        },
        {
          "id": "2",
          "name": "Giày thể thao nam Nike2",
          "price": 170,
          "image": "giay2.png",
          "views": 0,
          "quantity": 3
        },
        {
          "id": "3",
          "name": "Giày thể thao nam Nike3",
          "price": 160,
          "image": "giay3.png",
          "views": 0,
          "quantity": 2
        },
        {
          "id": "4",
          "name": "Giày thể thao nam Nike4",
          "price": 160,
          "image": "giay4.png",
          "views": 0,
          "quantity": 1
        },
        {
          "id": "5",
          "name": "Giày thể thao nam Nike5",
          "price": 150,
          "image": "giay5.png",
          "views": 0,
          "quantity": 2
        },
        {
          "id": "6",
          "name": "Giày thể thao nam Nike6",
          "price": 170,
          "image": "giay6.png",
          "views": 0,
          "quantity": 2
        }
      ],
      "total": 2380,
      "date": "2024-04-05 13:49:12",
      "status": "order"
    },
    {
      "id": "e58c",
      "name": "231231",
      "idUser": "-1",
      "phone": 231231,
      "address": "áđâsd",
      "products": [
        {
          "id": "1",
          "name": "Giày thể thao nam Nike1",
          "price": 150,
          "image": "giay1.png",
          "views": 0,
          "quantity": 5
        },
        {
          "id": "2",
          "name": "Giày thể thao nam Nike2",
          "price": 170,
          "image": "giay2.png",
          "views": 0,
          "quantity": 3
        },
        {
          "id": "3",
          "name": "Giày thể thao nam Nike3",
          "price": 160,
          "image": "giay3.png",
          "views": 0,
          "quantity": 2
        },
        {
          "id": "4",
          "name": "Giày thể thao nam Nike4",
          "price": 160,
          "image": "giay4.png",
          "views": 0,
          "quantity": 1
        },
        {
          "id": "5",
          "name": "Giày thể thao nam Nike5",
          "price": 150,
          "image": "giay5.png",
          "views": 0,
          "quantity": 2
        },
        {
          "id": "6",
          "name": "Giày thể thao nam Nike6",
          "price": 170,
          "image": "giay6.png",
          "views": 0,
          "quantity": 2
        }
      ],
      "total": 2380,
      "date": "2024-04-05 13:51:47",
      "status": "order"
    },
    {
      "id": "bb5f",
      "name": "231231",
      "idUser": "-1",
      "phone": 231231,
      "address": "áđâsd",
      "products": [
        {
          "id": "1",
          "name": "Giày thể thao nam Nike1",
          "price": 150,
          "image": "giay1.png",
          "views": 0,
          "quantity": 5
        },
        {
          "id": "2",
          "name": "Giày thể thao nam Nike2",
          "price": 170,
          "image": "giay2.png",
          "views": 0,
          "quantity": 3
        },
        {
          "id": "3",
          "name": "Giày thể thao nam Nike3",
          "price": 160,
          "image": "giay3.png",
          "views": 0,
          "quantity": 2
        },
        {
          "id": "4",
          "name": "Giày thể thao nam Nike4",
          "price": 160,
          "image": "giay4.png",
          "views": 0,
          "quantity": 1
        },
        {
          "id": "5",
          "name": "Giày thể thao nam Nike5",
          "price": 150,
          "image": "giay5.png",
          "views": 0,
          "quantity": 2
        },
        {
          "id": "6",
          "name": "Giày thể thao nam Nike6",
          "price": 170,
          "image": "giay6.png",
          "views": 0,
          "quantity": 2
        }
      ],
      "total": 2380,
      "date": "2024-04-05 13:51:48",
      "status": "order"
    },
    {
      "id": "82e2",
      "name": "231231",
      "idUser": "-1",
      "phone": 231231,
      "address": "áđâsd",
      "products": [
        {
          "id": "1",
          "name": "Giày thể thao nam Nike1",
          "price": 150,
          "image": "giay1.png",
          "views": 0,
          "quantity": 5
        },
        {
          "id": "2",
          "name": "Giày thể thao nam Nike2",
          "price": 170,
          "image": "giay2.png",
          "views": 0,
          "quantity": 3
        },
        {
          "id": "3",
          "name": "Giày thể thao nam Nike3",
          "price": 160,
          "image": "giay3.png",
          "views": 0,
          "quantity": 2
        },
        {
          "id": "4",
          "name": "Giày thể thao nam Nike4",
          "price": 160,
          "image": "giay4.png",
          "views": 0,
          "quantity": 1
        },
        {
          "id": "5",
          "name": "Giày thể thao nam Nike5",
          "price": 150,
          "image": "giay5.png",
          "views": 0,
          "quantity": 2
        },
        {
          "id": "6",
          "name": "Giày thể thao nam Nike6",
          "price": 170,
          "image": "giay6.png",
          "views": 0,
          "quantity": 2
        }
      ],
      "total": 2380,
      "date": "2024-04-05 13:51:48",
      "status": "order"
    },
    {
      "id": "0131",
      "name": "231231",
      "idUser": "-1",
      "phone": 231231,
      "address": "áđâsd",
      "products": [
        {
          "id": "1",
          "name": "Giày thể thao nam Nike1",
          "price": 150,
          "image": "giay1.png",
          "views": 0,
          "quantity": 5
        },
        {
          "id": "2",
          "name": "Giày thể thao nam Nike2",
          "price": 170,
          "image": "giay2.png",
          "views": 0,
          "quantity": 3
        },
        {
          "id": "3",
          "name": "Giày thể thao nam Nike3",
          "price": 160,
          "image": "giay3.png",
          "views": 0,
          "quantity": 2
        },
        {
          "id": "4",
          "name": "Giày thể thao nam Nike4",
          "price": 160,
          "image": "giay4.png",
          "views": 0,
          "quantity": 1
        },
        {
          "id": "5",
          "name": "Giày thể thao nam Nike5",
          "price": 150,
          "image": "giay5.png",
          "views": 0,
          "quantity": 2
        },
        {
          "id": "6",
          "name": "Giày thể thao nam Nike6",
          "price": 170,
          "image": "giay6.png",
          "views": 0,
          "quantity": 2
        }
      ],
      "total": 2380,
      "date": "2024-04-05 13:51:48",
      "status": "order"
    },
    {
      "id": "c422",
      "name": "phuoc",
      "idUser": "-1",
      "phone": 31231,
      "address": "đf",
      "products": [
        {
          "id": "1",
          "name": "Giày thể thao nam Nike1",
          "price": 150,
          "image": "giay1.png",
          "views": 0,
          "quantity": 5
        },
        {
          "id": "2",
          "name": "Giày thể thao nam Nike2",
          "price": 170,
          "image": "giay2.png",
          "views": 0,
          "quantity": 3
        },
        {
          "id": "3",
          "name": "Giày thể thao nam Nike3",
          "price": 160,
          "image": "giay3.png",
          "views": 0,
          "quantity": 2
        },
        {
          "id": "4",
          "name": "Giày thể thao nam Nike4",
          "price": 160,
          "image": "giay4.png",
          "views": 0,
          "quantity": 1
        },
        {
          "id": "5",
          "name": "Giày thể thao nam Nike5",
          "price": 150,
          "image": "giay5.png",
          "views": 0,
          "quantity": 2
        },
        {
          "id": "6",
          "name": "Giày thể thao nam Nike6",
          "price": 170,
          "image": "giay6.png",
          "views": 0,
          "quantity": 2
        }
      ],
      "total": 2380,
      "date": "2024-04-05 13:53:40",
      "status": "order"
    },
    {
      "id": "431f",
      "name": "phuoc",
      "idUser": "-1",
      "phone": 31231,
      "address": "đf",
      "products": [
        {
          "id": "1",
          "name": "Giày thể thao nam Nike1",
          "price": 150,
          "image": "giay1.png",
          "views": 0,
          "quantity": 5
        },
        {
          "id": "2",
          "name": "Giày thể thao nam Nike2",
          "price": 170,
          "image": "giay2.png",
          "views": 0,
          "quantity": 3
        },
        {
          "id": "3",
          "name": "Giày thể thao nam Nike3",
          "price": 160,
          "image": "giay3.png",
          "views": 0,
          "quantity": 2
        },
        {
          "id": "4",
          "name": "Giày thể thao nam Nike4",
          "price": 160,
          "image": "giay4.png",
          "views": 0,
          "quantity": 1
        },
        {
          "id": "5",
          "name": "Giày thể thao nam Nike5",
          "price": 150,
          "image": "giay5.png",
          "views": 0,
          "quantity": 2
        },
        {
          "id": "6",
          "name": "Giày thể thao nam Nike6",
          "price": 170,
          "image": "giay6.png",
          "views": 0,
          "quantity": 2
        }
      ],
      "total": 2380,
      "date": "2024-04-05 13:53:40",
      "status": "order"
    },
    {
      "id": "3ac4",
      "name": "phuoc",
      "idUser": "-1",
      "phone": 31231,
      "address": "đf",
      "products": [
        {
          "id": "1",
          "name": "Giày thể thao nam Nike1",
          "price": 150,
          "image": "giay1.png",
          "views": 0,
          "quantity": 5
        },
        {
          "id": "2",
          "name": "Giày thể thao nam Nike2",
          "price": 170,
          "image": "giay2.png",
          "views": 0,
          "quantity": 3
        },
        {
          "id": "3",
          "name": "Giày thể thao nam Nike3",
          "price": 160,
          "image": "giay3.png",
          "views": 0,
          "quantity": 2
        },
        {
          "id": "4",
          "name": "Giày thể thao nam Nike4",
          "price": 160,
          "image": "giay4.png",
          "views": 0,
          "quantity": 1
        },
        {
          "id": "5",
          "name": "Giày thể thao nam Nike5",
          "price": 150,
          "image": "giay5.png",
          "views": 0,
          "quantity": 2
        },
        {
          "id": "6",
          "name": "Giày thể thao nam Nike6",
          "price": 170,
          "image": "giay6.png",
          "views": 0,
          "quantity": 2
        }
      ],
      "total": 2380,
      "date": "2024-04-05 13:53:40",
      "status": "order"
    },
    {
      "id": "3b5a",
      "name": "phuoc",
      "idUser": "-1",
      "phone": 31231,
      "address": "đf",
      "products": [
        {
          "id": "1",
          "name": "Giày thể thao nam Nike1",
          "price": 150,
          "image": "giay1.png",
          "views": 0,
          "quantity": 5
        },
        {
          "id": "2",
          "name": "Giày thể thao nam Nike2",
          "price": 170,
          "image": "giay2.png",
          "views": 0,
          "quantity": 3
        },
        {
          "id": "3",
          "name": "Giày thể thao nam Nike3",
          "price": 160,
          "image": "giay3.png",
          "views": 0,
          "quantity": 2
        },
        {
          "id": "4",
          "name": "Giày thể thao nam Nike4",
          "price": 160,
          "image": "giay4.png",
          "views": 0,
          "quantity": 1
        },
        {
          "id": "5",
          "name": "Giày thể thao nam Nike5",
          "price": 150,
          "image": "giay5.png",
          "views": 0,
          "quantity": 2
        },
        {
          "id": "6",
          "name": "Giày thể thao nam Nike6",
          "price": 170,
          "image": "giay6.png",
          "views": 0,
          "quantity": 2
        }
      ],
      "total": 2380,
      "date": "2024-04-05 13:53:41",
      "status": "order"
    },
    {
      "id": "37d1",
      "name": "phuoc",
      "idUser": "-1",
      "phone": 31231231,
      "address": "dsadá",
      "products": [
        {
          "id": "1",
          "name": "Giày thể thao nam Nike1",
          "price": 150,
          "image": "giay1.png",
          "views": 0,
          "quantity": 5
        },
        {
          "id": "2",
          "name": "Giày thể thao nam Nike2",
          "price": 170,
          "image": "giay2.png",
          "views": 0,
          "quantity": 3
        },
        {
          "id": "3",
          "name": "Giày thể thao nam Nike3",
          "price": 160,
          "image": "giay3.png",
          "views": 0,
          "quantity": 2
        },
        {
          "id": "4",
          "name": "Giày thể thao nam Nike4",
          "price": 160,
          "image": "giay4.png",
          "views": 0,
          "quantity": 1
        },
        {
          "id": "5",
          "name": "Giày thể thao nam Nike5",
          "price": 150,
          "image": "giay5.png",
          "views": 0,
          "quantity": 2
        },
        {
          "id": "6",
          "name": "Giày thể thao nam Nike6",
          "price": 170,
          "image": "giay6.png",
          "views": 0,
          "quantity": 2
        }
      ],
      "total": 2380,
      "date": "2024-04-05 13:53:53",
      "status": "order"
    },
    {
      "id": "f468",
      "name": "phuoc",
      "idUser": "-1",
      "phone": 31231231,
      "address": "dsadá",
      "products": [
        {
          "id": "1",
          "name": "Giày thể thao nam Nike1",
          "price": 150,
          "image": "giay1.png",
          "views": 0,
          "quantity": 5
        },
        {
          "id": "2",
          "name": "Giày thể thao nam Nike2",
          "price": 170,
          "image": "giay2.png",
          "views": 0,
          "quantity": 3
        },
        {
          "id": "3",
          "name": "Giày thể thao nam Nike3",
          "price": 160,
          "image": "giay3.png",
          "views": 0,
          "quantity": 2
        },
        {
          "id": "4",
          "name": "Giày thể thao nam Nike4",
          "price": 160,
          "image": "giay4.png",
          "views": 0,
          "quantity": 1
        },
        {
          "id": "5",
          "name": "Giày thể thao nam Nike5",
          "price": 150,
          "image": "giay5.png",
          "views": 0,
          "quantity": 2
        },
        {
          "id": "6",
          "name": "Giày thể thao nam Nike6",
          "price": 170,
          "image": "giay6.png",
          "views": 0,
          "quantity": 2
        }
      ],
      "total": 2380,
      "date": "2024-04-05 13:53:53",
      "status": "order"
    },
    {
      "id": "750c",
      "name": "phuoc",
      "idUser": "-1",
      "phone": 31231231,
      "address": "dsadá",
      "products": [
        {
          "id": "1",
          "name": "Giày thể thao nam Nike1",
          "price": 150,
          "image": "giay1.png",
          "views": 0,
          "quantity": 5
        },
        {
          "id": "2",
          "name": "Giày thể thao nam Nike2",
          "price": 170,
          "image": "giay2.png",
          "views": 0,
          "quantity": 3
        },
        {
          "id": "3",
          "name": "Giày thể thao nam Nike3",
          "price": 160,
          "image": "giay3.png",
          "views": 0,
          "quantity": 2
        },
        {
          "id": "4",
          "name": "Giày thể thao nam Nike4",
          "price": 160,
          "image": "giay4.png",
          "views": 0,
          "quantity": 1
        },
        {
          "id": "5",
          "name": "Giày thể thao nam Nike5",
          "price": 150,
          "image": "giay5.png",
          "views": 0,
          "quantity": 2
        },
        {
          "id": "6",
          "name": "Giày thể thao nam Nike6",
          "price": 170,
          "image": "giay6.png",
          "views": 0,
          "quantity": 2
        }
      ],
      "total": 2380,
      "date": "2024-04-05 13:53:54",
      "status": "order"
    },
    {
      "id": "29da",
      "name": "đấ",
      "idUser": "-1",
      "phone": 213123,
      "address": "dâsđâs",
      "products": [
        {
          "id": "1",
          "name": "Giày thể thao nam Nike1",
          "price": 150,
          "image": "giay1.png",
          "views": 0,
          "quantity": 5
        },
        {
          "id": "2",
          "name": "Giày thể thao nam Nike2",
          "price": 170,
          "image": "giay2.png",
          "views": 0,
          "quantity": 3
        },
        {
          "id": "3",
          "name": "Giày thể thao nam Nike3",
          "price": 160,
          "image": "giay3.png",
          "views": 0,
          "quantity": 2
        },
        {
          "id": "4",
          "name": "Giày thể thao nam Nike4",
          "price": 160,
          "image": "giay4.png",
          "views": 0,
          "quantity": 1
        },
        {
          "id": "5",
          "name": "Giày thể thao nam Nike5",
          "price": 150,
          "image": "giay5.png",
          "views": 0,
          "quantity": 2
        },
        {
          "id": "6",
          "name": "Giày thể thao nam Nike6",
          "price": 170,
          "image": "giay6.png",
          "views": 0,
          "quantity": 2
        }
      ],
      "total": 2380,
      "date": "2024-04-05 13:54:18",
      "status": "order"
    },
    {
      "id": "5a5e",
      "name": "đấ",
      "idUser": "-1",
      "phone": 213123,
      "address": "dâsđâs",
      "products": [
        {
          "id": "1",
          "name": "Giày thể thao nam Nike1",
          "price": 150,
          "image": "giay1.png",
          "views": 0,
          "quantity": 5
        },
        {
          "id": "2",
          "name": "Giày thể thao nam Nike2",
          "price": 170,
          "image": "giay2.png",
          "views": 0,
          "quantity": 3
        },
        {
          "id": "3",
          "name": "Giày thể thao nam Nike3",
          "price": 160,
          "image": "giay3.png",
          "views": 0,
          "quantity": 2
        },
        {
          "id": "4",
          "name": "Giày thể thao nam Nike4",
          "price": 160,
          "image": "giay4.png",
          "views": 0,
          "quantity": 1
        },
        {
          "id": "5",
          "name": "Giày thể thao nam Nike5",
          "price": 150,
          "image": "giay5.png",
          "views": 0,
          "quantity": 2
        },
        {
          "id": "6",
          "name": "Giày thể thao nam Nike6",
          "price": 170,
          "image": "giay6.png",
          "views": 0,
          "quantity": 2
        }
      ],
      "total": 2380,
      "date": "2024-04-05 13:54:18",
      "status": "order"
    },
    {
      "id": "a987",
      "name": "đấ",
      "idUser": "-1",
      "phone": 213123,
      "address": "dâsđâs",
      "products": [
        {
          "id": "1",
          "name": "Giày thể thao nam Nike1",
          "price": 150,
          "image": "giay1.png",
          "views": 0,
          "quantity": 5
        },
        {
          "id": "2",
          "name": "Giày thể thao nam Nike2",
          "price": 170,
          "image": "giay2.png",
          "views": 0,
          "quantity": 3
        },
        {
          "id": "3",
          "name": "Giày thể thao nam Nike3",
          "price": 160,
          "image": "giay3.png",
          "views": 0,
          "quantity": 2
        },
        {
          "id": "4",
          "name": "Giày thể thao nam Nike4",
          "price": 160,
          "image": "giay4.png",
          "views": 0,
          "quantity": 1
        },
        {
          "id": "5",
          "name": "Giày thể thao nam Nike5",
          "price": 150,
          "image": "giay5.png",
          "views": 0,
          "quantity": 2
        },
        {
          "id": "6",
          "name": "Giày thể thao nam Nike6",
          "price": 170,
          "image": "giay6.png",
          "views": 0,
          "quantity": 2
        }
      ],
      "total": 2380,
      "date": "2024-04-05 13:54:19",
      "status": "order"
    },
    {
      "id": "40f2",
      "name": "đấ",
      "idUser": "-1",
      "phone": 213123,
      "address": "dâsđâs",
      "products": [
        {
          "id": "1",
          "name": "Giày thể thao nam Nike1",
          "price": 150,
          "image": "giay1.png",
          "views": 0,
          "quantity": 5
        },
        {
          "id": "2",
          "name": "Giày thể thao nam Nike2",
          "price": 170,
          "image": "giay2.png",
          "views": 0,
          "quantity": 3
        },
        {
          "id": "3",
          "name": "Giày thể thao nam Nike3",
          "price": 160,
          "image": "giay3.png",
          "views": 0,
          "quantity": 2
        },
        {
          "id": "4",
          "name": "Giày thể thao nam Nike4",
          "price": 160,
          "image": "giay4.png",
          "views": 0,
          "quantity": 1
        },
        {
          "id": "5",
          "name": "Giày thể thao nam Nike5",
          "price": 150,
          "image": "giay5.png",
          "views": 0,
          "quantity": 2
        },
        {
          "id": "6",
          "name": "Giày thể thao nam Nike6",
          "price": 170,
          "image": "giay6.png",
          "views": 0,
          "quantity": 2
        }
      ],
      "total": 2380,
      "date": "2024-04-05 13:54:19",
      "status": "order"
    },
    {
      "id": "ffd5",
      "name": "đấ",
      "idUser": "-1",
      "phone": 213123,
      "address": "dâsđâs",
      "products": [
        {
          "id": "1",
          "name": "Giày thể thao nam Nike1",
          "price": 150,
          "image": "giay1.png",
          "views": 0,
          "quantity": 5
        },
        {
          "id": "2",
          "name": "Giày thể thao nam Nike2",
          "price": 170,
          "image": "giay2.png",
          "views": 0,
          "quantity": 3
        },
        {
          "id": "3",
          "name": "Giày thể thao nam Nike3",
          "price": 160,
          "image": "giay3.png",
          "views": 0,
          "quantity": 2
        },
        {
          "id": "4",
          "name": "Giày thể thao nam Nike4",
          "price": 160,
          "image": "giay4.png",
          "views": 0,
          "quantity": 1
        },
        {
          "id": "5",
          "name": "Giày thể thao nam Nike5",
          "price": 150,
          "image": "giay5.png",
          "views": 0,
          "quantity": 2
        },
        {
          "id": "6",
          "name": "Giày thể thao nam Nike6",
          "price": 170,
          "image": "giay6.png",
          "views": 0,
          "quantity": 2
        }
      ],
      "total": 2380,
      "date": "2024-04-05 13:54:19",
      "status": "order"
    },
    {
      "id": "82e7",
      "name": "đấ",
      "idUser": "-1",
      "phone": 213123,
      "address": "dâsđâs",
      "products": [
        {
          "id": "1",
          "name": "Giày thể thao nam Nike1",
          "price": 150,
          "image": "giay1.png",
          "views": 0,
          "quantity": 5
        },
        {
          "id": "2",
          "name": "Giày thể thao nam Nike2",
          "price": 170,
          "image": "giay2.png",
          "views": 0,
          "quantity": 3
        },
        {
          "id": "3",
          "name": "Giày thể thao nam Nike3",
          "price": 160,
          "image": "giay3.png",
          "views": 0,
          "quantity": 2
        },
        {
          "id": "4",
          "name": "Giày thể thao nam Nike4",
          "price": 160,
          "image": "giay4.png",
          "views": 0,
          "quantity": 1
        },
        {
          "id": "5",
          "name": "Giày thể thao nam Nike5",
          "price": 150,
          "image": "giay5.png",
          "views": 0,
          "quantity": 2
        },
        {
          "id": "6",
          "name": "Giày thể thao nam Nike6",
          "price": 170,
          "image": "giay6.png",
          "views": 0,
          "quantity": 2
        }
      ],
      "total": 2380,
      "date": "2024-04-05 13:54:19",
      "status": "order"
    },
    {
      "id": "3740",
      "name": "đấ",
      "idUser": "-1",
      "phone": 213123,
      "address": "dâsđâs",
      "products": [
        {
          "id": "1",
          "name": "Giày thể thao nam Nike1",
          "price": 150,
          "image": "giay1.png",
          "views": 0,
          "quantity": 5
        },
        {
          "id": "2",
          "name": "Giày thể thao nam Nike2",
          "price": 170,
          "image": "giay2.png",
          "views": 0,
          "quantity": 3
        },
        {
          "id": "3",
          "name": "Giày thể thao nam Nike3",
          "price": 160,
          "image": "giay3.png",
          "views": 0,
          "quantity": 2
        },
        {
          "id": "4",
          "name": "Giày thể thao nam Nike4",
          "price": 160,
          "image": "giay4.png",
          "views": 0,
          "quantity": 1
        },
        {
          "id": "5",
          "name": "Giày thể thao nam Nike5",
          "price": 150,
          "image": "giay5.png",
          "views": 0,
          "quantity": 2
        },
        {
          "id": "6",
          "name": "Giày thể thao nam Nike6",
          "price": 170,
          "image": "giay6.png",
          "views": 0,
          "quantity": 2
        }
      ],
      "total": 2380,
      "date": "2024-04-05 13:54:19",
      "status": "order"
    },
    {
      "id": "fc32",
      "name": "hjkhjkhk",
      "phone": 1223,
      "address": "jhkjhjk",
      "products": [
        {
          "id": "1",
          "name": "Giày thể thao nam Nike1",
          "price": 150,
          "image": "giay1.png",
          "views": 0,
          "quantity": 5
        },
        {
          "id": "2",
          "name": "Giày thể thao nam Nike2",
          "price": 170,
          "image": "giay2.png",
          "views": 0,
          "quantity": 3
        },
        {
          "id": "3",
          "name": "Giày thể thao nam Nike3",
          "price": 160,
          "image": "giay3.png",
          "views": 0,
          "quantity": 2
        },
        {
          "id": "4",
          "name": "Giày thể thao nam Nike4",
          "price": 160,
          "image": "giay4.png",
          "views": 0,
          "quantity": 1
        },
        {
          "id": "5",
          "name": "Giày thể thao nam Nike5",
          "price": 150,
          "image": "giay5.png",
          "views": 0,
          "quantity": 2
        },
        {
          "id": "6",
          "name": "Giày thể thao nam Nike6",
          "price": 170,
          "image": "giay6.png",
          "views": 0,
          "quantity": 2
        }
      ],
      "idUser": "-1",
      "total": 2380,
      "date": "2024-04-05 15:01:06",
      "status": "order"
    },
    {
      "id": "e283",
      "name": "mlk;l",
      "phone": 5465465,
      "address": "l;l';",
      "products": [
        {
          "id": "1",
          "name": "Giày thể thao nam Nike1",
          "price": 150,
          "image": "giay1.png",
          "views": 0,
          "quantity": 5
        },
        {
          "id": "2",
          "name": "Giày thể thao nam Nike2",
          "price": 170,
          "image": "giay2.png",
          "views": 0,
          "quantity": 3
        },
        {
          "id": "3",
          "name": "Giày thể thao nam Nike3",
          "price": 160,
          "image": "giay3.png",
          "views": 0,
          "quantity": 2
        },
        {
          "id": "4",
          "name": "Giày thể thao nam Nike4",
          "price": 160,
          "image": "giay4.png",
          "views": 0,
          "quantity": 1
        },
        {
          "id": "5",
          "name": "Giày thể thao nam Nike5",
          "price": 150,
          "image": "giay5.png",
          "views": 0,
          "quantity": 2
        },
        {
          "id": "6",
          "name": "Giày thể thao nam Nike6",
          "price": 170,
          "image": "giay6.png",
          "views": 0,
          "quantity": 2
        }
      ],
      "idUser": "-1",
      "total": 2380,
      "date": "2024-04-05 15:01:41",
      "status": "order"
    },
    {
      "id": "f3b6",
      "name": "ád",
      "phone": 231,
      "address": "ád",
      "products": [
        {
          "id": "1",
          "name": "Giày thể thao nam Nike1",
          "price": 150,
          "image": "giay1.png",
          "views": 0,
          "quantity": 5
        },
        {
          "id": "2",
          "name": "Giày thể thao nam Nike2",
          "price": 170,
          "image": "giay2.png",
          "views": 0,
          "quantity": 3
        },
        {
          "id": "3",
          "name": "Giày thể thao nam Nike3",
          "price": 160,
          "image": "giay3.png",
          "views": 0,
          "quantity": 2
        },
        {
          "id": "4",
          "name": "Giày thể thao nam Nike4",
          "price": 160,
          "image": "giay4.png",
          "views": 0,
          "quantity": 1
        },
        {
          "id": "5",
          "name": "Giày thể thao nam Nike5",
          "price": 150,
          "image": "giay5.png",
          "views": 0,
          "quantity": 2
        },
        {
          "id": "6",
          "name": "Giày thể thao nam Nike6",
          "price": 170,
          "image": "giay6.png",
          "views": 0,
          "quantity": 2
        }
      ],
      "idUser": "-1",
      "total": 2380,
      "date": "2024-04-05 15:04:23",
      "status": "order"
    }
  ]
}